[
    {
        "type": "COURSE",
        "key": "SEASIAN 10A",
        "prefix": "SEASIAN",
        "number": "10A",
        "title": "Introduction to the Civilization of Southeast Asia (Mainland Southeast Asia)",
        "min_units": 4.0,
        "max_units": 4.0,
        "articulations": []
    },
    {
        "type": "COURSE",
        "key": "SEASIAN 10B",
        "prefix": "SEASIAN",
        "number": "10B",
        "title": "Introduction to the Civilization of Southeast Asia (Insular Southeast Asia)",
        "min_units": 4.0,
        "max_units": 4.0,
        "articulations": []
    }
]