[
    {
        "type": "COURSE",
        "subject": "International Studies",
        "prefix": "BAIS",
        "number": "100",
        "key": "BAIS 100",
        "title": "Introduction to International Studies",
        "min_units": 4.0,
        "max_units": 4.0,
        "articulations": []
    },
    {
        "type": "COURSE",
        "subject": "International Studies",
        "prefix": "BAIS",
        "number": "103",
        "key": "BAIS 103",
        "title": "The Global Economy",
        "min_units": 4.0,
        "max_units": 4.0,
        "articulations": []
    },
    {
        "type": "COURSE",
        "subject": "International Studies",
        "prefix": "BAIS",
        "number": "201",
        "key": "BAIS 201",
        "title": "Research Methods",
        "min_units": 4.0,
        "max_units": 4.0,
        "articulations": []
    }
]