[
    {
        "type": "COURSE",
        "key": "ASTR 2",
        "prefix": "ASTR",
        "number": "2",
        "title": "Overview of the Universe",
        "min_units": 5.0,
        "max_units": 5.0,
        "articulations": [
            {
                "sending_name": "Allan Hancock College",
                "sending_articulation": {
                    "type": "COURSE",
                    "conjunction": "AND",
                    "courses": [
                        {
                            "prefix": "ASTR",
                            "number": "100",
                            "title": "Elementary Astronomy",
                            "notes": [],
                            "min_units": 3.0,
                            "max_units": 3.0
                        }
                    ],
                    "children": [],
                    "notes": []
                }
            },
            {
                "sending_name": "Cabrillo College",
                "sending_articulation": {
                    "type": "COURSE",
                    "conjunction": "AND",
                    "courses": [
                        {
                            "prefix": "ASTRO",
                            "number": "4",
                            "title": "Stars, Galaxies, and the Origin of the Universe",
                            "notes": [],
                            "min_units": 3.0,
                            "max_units": 3.0
                        }
                    ],
                    "children": [],
                    "notes": []
                }
            },
            {
                "sending_name": "Contra Costa College",
                "sending_articulation": {
                    "type": "COURSE",
                    "conjunction": "AND",
                    "courses": [
                        {
                            "prefix": "ASTRO",
                            "number": "120",
                            "title": "Elementary Astronomy",
                            "notes": [],
                            "min_units": 3.0,
                            "max_units": 3.0
                        }
                    ],
                    "children": [],
                    "notes": []
                }
            },
            {
                "sending_name": "Cuyamaca College",
                "sending_articulation": {
                    "type": "COURSE",
                    "conjunction": "AND",
                    "courses": [
                        {
                            "prefix": "ASTR",
                            "number": "110",
                            "title": "Descriptive Astronomy",
                            "notes": [],
                            "min_units": 3.0,
                            "max_units": 3.0
                        }
                    ],
                    "children": [],
                    "notes": []
                }
            },
            {
                "sending_name": "Evergreen Valley College",
                "sending_articulation": {
                    "type": "COURSE",
                    "conjunction": "AND",
                    "courses": [
                        {
                            "prefix": "ASTRO",
                            "number": "010",
                            "title": "Introduction to Astronomy",
                            "notes": [],
                            "min_units": 3.0,
                            "max_units": 3.0
                        }
                    ],
                    "children": [],
                    "notes": []
                }
            },
            {
                "sending_name": "Glendale Community College",
                "sending_articulation": {
                    "type": "COURSE",
                    "conjunction": "AND",
                    "courses": [
                        {
                            "prefix": "ASTRO",
                            "number": "110",
                            "title": "Astronomy of the Solar System",
                            "notes": [],
                            "min_units": 3.0,
                            "max_units": 3.0
                        },
                        {
                            "prefix": "ASTRO",
                            "number": "120",
                            "title": "Astronomy of Stars and Galaxies",
                            "notes": [],
                            "min_units": 3.0,
                            "max_units": 3.0
                        }
                    ],
                    "children": [],
                    "notes": []
                }
            },
            {
                "sending_name": "Grossmont College",
                "sending_articulation": {
                    "type": "COURSE",
                    "conjunction": "AND",
                    "courses": [
                        {
                            "prefix": "ASTR",
                            "number": "110",
                            "title": "Descriptive Astronomy",
                            "notes": [],
                            "min_units": 3.0,
                            "max_units": 3.0
                        }
                    ],
                    "children": [],
                    "notes": []
                }
            },
            {
                "sending_name": "Irvine Valley College",
                "sending_articulation": {
                    "type": "GROUP",
                    "conjunction": "OR",
                    "courses": [],
                    "children": [
                        {
                            "type": "COURSE",
                            "conjunction": "AND",
                            "courses": [
                                {
                                    "prefix": "ASTR",
                                    "number": "20",
                                    "title": "General Astronomy",
                                    "notes": [],
                                    "min_units": 3.0,
                                    "max_units": 3.0
                                }
                            ],
                            "children": [],
                            "notes": []
                        },
                        {
                            "type": "COURSE",
                            "conjunction": "AND",
                            "courses": [
                                {
                                    "prefix": "ASTR",
                                    "number": "20H",
                                    "title": "General Astronomy Honors",
                                    "notes": [],
                                    "min_units": 3.0,
                                    "max_units": 3.0
                                }
                            ],
                            "children": [],
                            "notes": []
                        }
                    ],
                    "notes": []
                }
            },
            {
                "sending_name": "Las Positas College",
                "sending_articulation": {
                    "type": "COURSE",
                    "conjunction": "AND",
                    "courses": [
                        {
                            "prefix": "ASTR",
                            "number": "32",
                            "title": "Introduction to Astronomy: Stars and the Universe",
                            "notes": [],
                            "min_units": 3.0,
                            "max_units": 3.0
                        }
                    ],
                    "children": [],
                    "notes": []
                }
            },
            {
                "sending_name": "Los Angeles Pierce College",
                "sending_articulation": {
                    "type": "COURSE",
                    "conjunction": "AND",
                    "courses": [
                        {
                            "prefix": "ASTRON",
                            "number": "001",
                            "title": "Elementary Astronomy",
                            "notes": [],
                            "min_units": 3.0,
                            "max_units": 3.0
                        }
                    ],
                    "children": [],
                    "notes": []
                }
            },
            {
                "sending_name": "West Los Angeles College",
                "sending_articulation": {
                    "type": "COURSE",
                    "conjunction": "AND",
                    "courses": [
                        {
                            "prefix": "ASTRON",
                            "number": "001",
                            "title": "Elementary Astronomy",
                            "notes": [],
                            "min_units": 3.0,
                            "max_units": 3.0
                        }
                    ],
                    "children": [],
                    "notes": []
                }
            }
        ]
    },
    {
        "type": "COURSE",
        "key": "ASTR 19",
        "prefix": "ASTR",
        "number": "19",
        "title": "Practical Programming for the Sciences",
        "min_units": 5.0,
        "max_units": 5.0,
        "articulations": []
    }
]