[
    {
        "type": "COURSE",
        "subject": "Athletics",
        "prefix": "ATHL",
        "number": "1ST",
        "key": "ATHL 1ST",
        "title": "Selected Topics",
        "min_units": 1.0,
        "max_units": 1.0,
        "articulations": []
    },
    {
        "type": "COURSE",
        "subject": "Athletics",
        "prefix": "ATHL",
        "number": "160",
        "key": "ATHL 160",
        "title": "Intercoll. Baseball",
        "min_units": 1.0,
        "max_units": 1.0,
        "articulations": []
    },
    {
        "type": "COURSE",
        "subject": "Athletics",
        "prefix": "ATHL",
        "number": "161",
        "key": "ATHL 161",
        "title": "Intercoll.Basketball",
        "min_units": 1.0,
        "max_units": 1.0,
        "articulations": []
    },
    {
        "type": "COURSE",
        "subject": "Athletics",
        "prefix": "ATHL",
        "number": "163",
        "key": "ATHL 163",
        "title": "Intercoll.Cross Country",
        "min_units": 1.0,
        "max_units": 1.0,
        "articulations": []
    },
    {
        "type": "COURSE",
        "subject": "Athletics",
        "prefix": "ATHL",
        "number": "164",
        "key": "ATHL 164",
        "title": "Intercoll.Football",
        "min_units": 1.0,
        "max_units": 1.0,
        "articulations": []
    },
    {
        "type": "COURSE",
        "subject": "Athletics",
        "prefix": "ATHL",
        "number": "165",
        "key": "ATHL 165",
        "title": "Intercoll.Golf",
        "min_units": 1.0,
        "max_units": 1.0,
        "articulations": []
    },
    {
        "type": "COURSE",
        "subject": "Athletics",
        "prefix": "ATHL",
        "number": "166",
        "key": "ATHL 166",
        "title": "Intercoll.Soccer",
        "min_units": 1.0,
        "max_units": 1.0,
        "articulations": []
    },
    {
        "type": "COURSE",
        "subject": "Athletics",
        "prefix": "ATHL",
        "number": "167",
        "key": "ATHL 167",
        "title": "Intercoll.Softball",
        "min_units": 1.0,
        "max_units": 1.0,
        "articulations": []
    },
    {
        "type": "COURSE",
        "subject": "Athletics",
        "prefix": "ATHL",
        "number": "168",
        "key": "ATHL 168",
        "title": "Intercoll.Tennis",
        "min_units": 1.0,
        "max_units": 1.0,
        "articulations": []
    },
    {
        "type": "COURSE",
        "subject": "Athletics",
        "prefix": "ATHL",
        "number": "169",
        "key": "ATHL 169",
        "title": "Intercoll.Track & Field",
        "min_units": 1.0,
        "max_units": 1.0,
        "articulations": []
    },
    {
        "type": "COURSE",
        "subject": "Athletics",
        "prefix": "ATHL",
        "number": "170",
        "key": "ATHL 170",
        "title": "Intercoll.Volleyball",
        "min_units": 1.0,
        "max_units": 1.0,
        "articulations": []
    },
    {
        "type": "COURSE",
        "subject": "Athletics",
        "prefix": "ATHL",
        "number": "171",
        "key": "ATHL 171",
        "title": "Intercoll.Swimming & Diving",
        "min_units": 1.0,
        "max_units": 1.0,
        "articulations": []
    },
    {
        "type": "COURSE",
        "subject": "Athletics",
        "prefix": "ATHL",
        "number": "172",
        "key": "ATHL 172",
        "title": "Intercoll. WaterPolo-M",
        "min_units": 1.0,
        "max_units": 1.0,
        "articulations": []
    },
    {
        "type": "COURSE",
        "subject": "Athletics",
        "prefix": "ATHL",
        "number": "173",
        "key": "ATHL 173",
        "title": "Intercoll.Water Polo-W",
        "min_units": 1.0,
        "max_units": 1.0,
        "articulations": []
    }
]