[
    {
        "type": "COURSE",
        "prefix": "AST",
        "number": "010C",
        "key": "AST 010C",
        "title": "Introduction to Cosmology",
        "min_units": 3.0,
        "max_units": 3.0,
        "articulations": [
            {
                "sending_name": "Lassen Community College",
                "sending_articulation": {
                    "type": "COURSE",
                    "conjunction": "AND",
                    "courses": [
                        {
                            "prefix": "ASTR",
                            "number": "1",
                            "key": "ASTR 1",
                            "title": "Introduction to Astronomy",
                            "notes": [
                                "Course is articulated in more than one agreement but credit can only apply to one"
                            ],
                            "min_units": 4.0,
                            "max_units": 4.0
                        }
                    ],
                    "children": [],
                    "notes": []
                }
            }
        ]
    },
    {
        "type": "COURSE",
        "prefix": "AST",
        "number": "010G",
        "key": "AST 010G",
        "title": "Introduction to Stars, Galaxies, & the Universe",
        "min_units": 3.0,
        "max_units": 3.0,
        "articulations": [
            {
                "sending_name": "Chaffey College",
                "sending_articulation": {
                    "type": "COURSE",
                    "conjunction": "AND",
                    "courses": [
                        {
                            "prefix": "ASTRON",
                            "number": "26",
                            "key": "ASTRON 26",
                            "title": "Stars and Galaxies",
                            "notes": [],
                            "min_units": 3.0,
                            "max_units": 3.0
                        }
                    ],
                    "children": [],
                    "notes": []
                }
            },
            {
                "sending_name": "Foothill College",
                "sending_articulation": {
                    "type": "GROUP",
                    "conjunction": "OR",
                    "courses": [],
                    "children": [
                        {
                            "type": "COURSE",
                            "conjunction": "AND",
                            "courses": [
                                {
                                    "prefix": "ASTR",
                                    "number": "10B",
                                    "key": "ASTR 10B",
                                    "title": "General Astronomy: Stars, Galaxies, Cosmology",
                                    "notes": [],
                                    "min_units": 5.0,
                                    "max_units": 5.0
                                }
                            ],
                            "children": [],
                            "notes": []
                        },
                        {
                            "type": "COURSE",
                            "conjunction": "AND",
                            "courses": [
                                {
                                    "prefix": "ASTR",
                                    "number": "10BH",
                                    "key": "ASTR 10BH",
                                    "title": "Honors General Astronomy: Stars, Galaxies, Cosmology",
                                    "notes": [],
                                    "min_units": 5.0,
                                    "max_units": 5.0
                                }
                            ],
                            "children": [],
                            "notes": []
                        }
                    ],
                    "notes": []
                }
            },
            {
                "sending_name": "Fresno City College",
                "sending_articulation": {
                    "type": "COURSE",
                    "conjunction": "AND",
                    "courses": [
                        {
                            "prefix": "ASTRO",
                            "number": "10",
                            "key": "ASTRO 10",
                            "title": "Basic Astronomy",
                            "notes": [],
                            "min_units": 4.0,
                            "max_units": 4.0
                        }
                    ],
                    "children": [],
                    "notes": []
                }
            },
            {
                "sending_name": "Glendale Community College",
                "sending_articulation": {
                    "type": "COURSE",
                    "conjunction": "AND",
                    "courses": [
                        {
                            "prefix": "ASTRO",
                            "number": "120",
                            "key": "ASTRO 120",
                            "title": "Astronomy of Stars and Galaxies",
                            "notes": [],
                            "min_units": 3.0,
                            "max_units": 3.0
                        }
                    ],
                    "children": [],
                    "notes": []
                }
            },
            {
                "sending_name": "Lassen Community College",
                "sending_articulation": {
                    "type": "COURSE",
                    "conjunction": "AND",
                    "courses": [
                        {
                            "prefix": "ASTR",
                            "number": "1",
                            "key": "ASTR 1",
                            "title": "Introduction to Astronomy",
                            "notes": [
                                "Course is articulated in more than one agreement but credit can only apply to one"
                            ],
                            "min_units": 4.0,
                            "max_units": 4.0
                        }
                    ],
                    "children": [],
                    "notes": []
                }
            },
            {
                "sending_name": "Moorpark College",
                "sending_articulation": {
                    "type": "COURSE",
                    "conjunction": "AND",
                    "courses": [
                        {
                            "prefix": "AST",
                            "number": "M01",
                            "key": "AST M01",
                            "title": "An Introduction to Astronomy",
                            "notes": [],
                            "min_units": 3.0,
                            "max_units": 3.0
                        }
                    ],
                    "children": [],
                    "notes": []
                }
            },
            {
                "sending_name": "Ohlone College",
                "sending_articulation": {
                    "type": "COURSE",
                    "conjunction": "AND",
                    "courses": [
                        {
                            "prefix": "ASTR",
                            "number": "101B",
                            "key": "ASTR 101B",
                            "title": "General Astronomy Beyond the Solar System",
                            "notes": [],
                            "min_units": 3.0,
                            "max_units": 3.0
                        }
                    ],
                    "children": [],
                    "notes": []
                }
            },
            {
                "sending_name": "Santa Rosa Junior College",
                "sending_articulation": {
                    "type": "COURSE",
                    "conjunction": "AND",
                    "courses": [
                        {
                            "prefix": "ASTR",
                            "number": "3",
                            "key": "ASTR 3",
                            "title": "Stellar Astronomy",
                            "notes": [],
                            "min_units": 3.0,
                            "max_units": 3.0
                        }
                    ],
                    "children": [],
                    "notes": []
                }
            },
            {
                "sending_name": "Ventura College",
                "sending_articulation": {
                    "type": "COURSE",
                    "conjunction": "AND",
                    "courses": [
                        {
                            "prefix": "AST",
                            "number": "V01",
                            "key": "AST V01",
                            "title": "Elementary Astronomy",
                            "notes": [],
                            "min_units": 3.0,
                            "max_units": 3.0
                        }
                    ],
                    "children": [],
                    "notes": []
                }
            }
        ]
    },
    {
        "type": "COURSE",
        "prefix": "AST",
        "number": "010L",
        "key": "AST 010L",
        "title": "Observational Astronomy Lab",
        "min_units": 1.0,
        "max_units": 1.0,
        "articulations": [
            {
                "sending_name": "Folsom Lake College",
                "sending_articulation": {
                    "type": "COURSE",
                    "conjunction": "AND",
                    "courses": [
                        {
                            "prefix": "ASTR",
                            "number": "400",
                            "key": "ASTR 400",
                            "title": "Astronomy Laboratory",
                            "notes": [],
                            "min_units": 1.0,
                            "max_units": 1.0
                        }
                    ],
                    "children": [],
                    "notes": []
                }
            },
            {
                "sending_name": "Foothill College",
                "sending_articulation": {
                    "type": "COURSE",
                    "conjunction": "AND",
                    "courses": [
                        {
                            "prefix": "ASTR",
                            "number": "10L",
                            "key": "ASTR 10L",
                            "title": "Astronomy Laboratory",
                            "notes": [],
                            "min_units": 1.0,
                            "max_units": 1.0
                        }
                    ],
                    "children": [],
                    "notes": []
                }
            },
            {
                "sending_name": "Lassen Community College",
                "sending_articulation": {
                    "type": "COURSE",
                    "conjunction": "AND",
                    "courses": [
                        {
                            "prefix": "ASTR",
                            "number": "1",
                            "key": "ASTR 1",
                            "title": "Introduction to Astronomy",
                            "notes": [
                                "Course is articulated in more than one agreement but credit can only apply to one"
                            ],
                            "min_units": 4.0,
                            "max_units": 4.0
                        }
                    ],
                    "children": [],
                    "notes": []
                }
            },
            {
                "sending_name": "Moorpark College",
                "sending_articulation": {
                    "type": "COURSE",
                    "conjunction": "AND",
                    "courses": [
                        {
                            "prefix": "AST",
                            "number": "M01L",
                            "key": "AST M01L",
                            "title": "An Introduction to Astronomy Laboratory",
                            "notes": [],
                            "min_units": 1.0,
                            "max_units": 1.0
                        }
                    ],
                    "children": [],
                    "notes": []
                }
            }
        ]
    },
    {
        "type": "COURSE",
        "prefix": "AST",
        "number": "010S",
        "key": "AST 010S",
        "title": "Astronomy of the Solar System",
        "min_units": 3.0,
        "max_units": 3.0,
        "articulations": [
            {
                "sending_name": "Foothill College",
                "sending_articulation": {
                    "type": "COURSE",
                    "conjunction": "AND",
                    "courses": [
                        {
                            "prefix": "ASTR",
                            "number": "10A",
                            "key": "ASTR 10A",
                            "title": "General Astronomy: Solar System",
                            "notes": [],
                            "min_units": 5.0,
                            "max_units": 5.0
                        }
                    ],
                    "children": [],
                    "notes": []
                }
            },
            {
                "sending_name": "Glendale Community College",
                "sending_articulation": {
                    "type": "COURSE",
                    "conjunction": "AND",
                    "courses": [
                        {
                            "prefix": "ASTRO",
                            "number": "110",
                            "key": "ASTRO 110",
                            "title": "Astronomy of the Solar System",
                            "notes": [],
                            "min_units": 3.0,
                            "max_units": 3.0
                        }
                    ],
                    "children": [],
                    "notes": []
                }
            },
            {
                "sending_name": "Santa Rosa Junior College",
                "sending_articulation": {
                    "type": "COURSE",
                    "conjunction": "AND",
                    "courses": [
                        {
                            "prefix": "ASTR",
                            "number": "4",
                            "key": "ASTR 4",
                            "title": "Astronomy of the Solar System",
                            "notes": [],
                            "min_units": 3.0,
                            "max_units": 3.0
                        }
                    ],
                    "children": [],
                    "notes": []
                }
            }
        ]
    },
    {
        "type": "COURSE",
        "prefix": "AST",
        "number": "025",
        "key": "AST 025",
        "title": "Introduction to Modern Astronomy & Astrophysics",
        "min_units": 4.0,
        "max_units": 4.0,
        "articulations": [
            {
                "sending_name": "Folsom Lake College",
                "sending_articulation": {
                    "type": "COURSE",
                    "conjunction": "AND",
                    "courses": [
                        {
                            "prefix": "ASTR",
                            "number": "300",
                            "key": "ASTR 300",
                            "title": "Introduction to Astronomy",
                            "notes": [],
                            "min_units": 3.0,
                            "max_units": 3.0
                        },
                        {
                            "prefix": "ASTR",
                            "number": "400",
                            "key": "ASTR 400",
                            "title": "Astronomy Laboratory",
                            "notes": [],
                            "min_units": 1.0,
                            "max_units": 1.0
                        }
                    ],
                    "children": [],
                    "notes": [
                        "Complete entire sequence at same institution prior to transfer"
                    ]
                }
            }
        ]
    }
]